[
    {
      "_id": "61f5ab10fbed3e030942dad6",
      "index": 0,
      "title": "aute",
      "genger": "enim",
      "declension": {
        "nominative": {
          "singular": "enim",
          "plural": "officia"
        },
        "genitive": {
          "singular": "esse",
          "plural": "consectetur"
        },
        "dative": {
          "singular": "Lorem",
          "plural": "anim"
        },
        "accusative": {
          "singular": "quis",
          "plural": "cillum"
        },
        "instrumental": {
          "singular": "nostrud",
          "plural": "ut"
        },
        "prepositional": {
          "singular": "mollit",
          "plural": "elit"
        }
      },
      "picture": "http://placehold.it/32x32",
      "tags": [
        "aliquip",
        "elit",
        "consectetur",
        "excepteur"
      ]
    },
    {
      "_id": "61f5ab101ea8e8971d0e51bd",
      "index": 1,
      "title": "Lorem",
      "genger": "commodo",
      "declension": {
        "nominative": {
          "singular": "anim",
          "plural": "qui"
        },
        "genitive": {
          "singular": "fugiat",
          "plural": "ullamco"
        },
        "dative": {
          "singular": "dolore",
          "plural": "eu"
        },
        "accusative": {
          "singular": "nostrud",
          "plural": "mollit"
        },
        "instrumental": {
          "singular": "proident",
          "plural": "et"
        },
        "prepositional": {
          "singular": "est",
          "plural": "minim"
        }
      },
      "picture": "http://placehold.it/32x32",
      "tags": [
        "ad",
        "ut",
        "nulla",
        "fugiat"
      ]
    },
    {
      "_id": "61f5ab108b02ba391fd9e57f",
      "index": 2,
      "title": "veniam",
      "genger": "laboris",
      "declension": {
        "nominative": {
          "singular": "amet",
          "plural": "irure"
        },
        "genitive": {
          "singular": "deserunt",
          "plural": "sint"
        },
        "dative": {
          "singular": "ullamco",
          "plural": "ut"
        },
        "accusative": {
          "singular": "deserunt",
          "plural": "adipisicing"
        },
        "instrumental": {
          "singular": "ex",
          "plural": "est"
        },
        "prepositional": {
          "singular": "sunt",
          "plural": "voluptate"
        }
      },
      "picture": "http://placehold.it/32x32",
      "tags": [
        "sunt",
        "culpa",
        "excepteur",
        "ea"
      ]
    },
    {
      "_id": "61f5ab10c93718bc6739f780",
      "index": 3,
      "title": "consequat",
      "genger": "sit",
      "declension": {
        "nominative": {
          "singular": "laborum",
          "plural": "adipisicing"
        },
        "genitive": {
          "singular": "veniam",
          "plural": "deserunt"
        },
        "dative": {
          "singular": "cillum",
          "plural": "sunt"
        },
        "accusative": {
          "singular": "elit",
          "plural": "Lorem"
        },
        "instrumental": {
          "singular": "velit",
          "plural": "labore"
        },
        "prepositional": {
          "singular": "eiusmod",
          "plural": "ad"
        }
      },
      "picture": "http://placehold.it/32x32",
      "tags": [
        "pariatur",
        "laboris",
        "tempor",
        "anim"
      ]
    },
    {
      "_id": "61f5ab100d5c3eec81fe7333",
      "index": 4,
      "title": "id",
      "genger": "esse",
      "declension": {
        "nominative": {
          "singular": "qui",
          "plural": "ea"
        },
        "genitive": {
          "singular": "consectetur",
          "plural": "est"
        },
        "dative": {
          "singular": "do",
          "plural": "velit"
        },
        "accusative": {
          "singular": "et",
          "plural": "cillum"
        },
        "instrumental": {
          "singular": "consequat",
          "plural": "reprehenderit"
        },
        "prepositional": {
          "singular": "sit",
          "plural": "duis"
        }
      },
      "picture": "http://placehold.it/32x32",
      "tags": [
        "deserunt",
        "adipisicing",
        "in",
        "veniam"
      ]
    },
    {
      "_id": "61f5ab108a01751803e9d847",
      "index": 5,
      "title": "consectetur",
      "genger": "anim",
      "declension": {
        "nominative": {
          "singular": "incididunt",
          "plural": "exercitation"
        },
        "genitive": {
          "singular": "cillum",
          "plural": "nostrud"
        },
        "dative": {
          "singular": "eiusmod",
          "plural": "magna"
        },
        "accusative": {
          "singular": "deserunt",
          "plural": "voluptate"
        },
        "instrumental": {
          "singular": "minim",
          "plural": "amet"
        },
        "prepositional": {
          "singular": "irure",
          "plural": "mollit"
        }
      },
      "picture": "http://placehold.it/32x32",
      "tags": [
        "esse",
        "eu",
        "amet",
        "cillum"
      ]
    }
  ]